calver/__init__.py
calver/integration.py
calver-2025.4.17.dist-info/licenses/LICENSE
calver-2025.4.17.dist-info/METADATA
calver-2025.4.17.dist-info/WHEEL
calver-2025.4.17.dist-info/entry_points.txt
calver-2025.4.17.dist-info/top_level.txt
calver-2025.4.17.dist-info/RECORD
