Metadata-Version: 2.4
Name: calver
Version: 2025.4.17
Summary: Setuptools extension for CalVer package versions
Author-email: Dustin Ingram <di@python.org>
License-Expression: Apache-2.0
Project-URL: Homepage, https://github.com/di/calver
Project-URL: Repository, https://github.com/di/calver
Keywords: calver
Classifier: Intended Audience :: Developers
Classifier: Topic :: Software Development :: Build Tools
Classifier: Programming Language :: Python :: 3
Requires-Python: >=3.9
License-File: LICENSE
Dynamic: license-file
